odoo8_addon_contract_payment_mode-8.0.1.0.0.99.dev21-py3.8-nspkg.pth
odoo_addons/contract_payment_mode/README.rst
odoo_addons/contract_payment_mode/__init__.py
odoo_addons/contract_payment_mode/__openerp__.py
odoo_addons/contract_payment_mode/hooks.py
odoo_addons/contract_payment_mode/i18n/ca.po
odoo_addons/contract_payment_mode/i18n/contract_payment_mode.pot
odoo_addons/contract_payment_mode/i18n/de.po
odoo_addons/contract_payment_mode/i18n/el_GR.po
odoo_addons/contract_payment_mode/i18n/es.po
odoo_addons/contract_payment_mode/i18n/es_MX.po
odoo_addons/contract_payment_mode/i18n/fi.po
odoo_addons/contract_payment_mode/i18n/fr.po
odoo_addons/contract_payment_mode/i18n/it.po
odoo_addons/contract_payment_mode/i18n/nl.po
odoo_addons/contract_payment_mode/i18n/pt_BR.po
odoo_addons/contract_payment_mode/i18n/sk_SK.po
odoo_addons/contract_payment_mode/i18n/sl.po
odoo_addons/contract_payment_mode/i18n/zh_CN.po
odoo_addons/contract_payment_mode/models/__init__.py
odoo_addons/contract_payment_mode/models/contract.py
odoo_addons/contract_payment_mode/static/description/icon.png
odoo_addons/contract_payment_mode/test/contract_payment_mode.yml
odoo_addons/contract_payment_mode/tests/__init__.py
odoo_addons/contract_payment_mode/tests/test_contract_payment_init.py
odoo_addons/contract_payment_mode/views/contract_view.xml
odoo8_addon_contract_payment_mode-8.0.1.0.0.99.dev21.dist-info/METADATA
odoo8_addon_contract_payment_mode-8.0.1.0.0.99.dev21.dist-info/WHEEL
odoo8_addon_contract_payment_mode-8.0.1.0.0.99.dev21.dist-info/namespace_packages.txt
odoo8_addon_contract_payment_mode-8.0.1.0.0.99.dev21.dist-info/top_level.txt
odoo8_addon_contract_payment_mode-8.0.1.0.0.99.dev21.dist-info/RECORD
